crunchdao_crunch_example/__init__.py
crunchdao_crunch_example/models/neural_network/resources/neural_network_model.pkl
crunchdao_crunch_example/models/neural_network/resources/scaler.pkl
crunchdao_crunch_example/models/neural_network/submissions/main.py
crunchdao_crunch_example/models/neural_network/submissions/requirements.txt
crunchdao_crunch_example/models/random_forest/resources/random_forest_model.pkl
crunchdao_crunch_example/models/random_forest/resources/scaler.pkl
crunchdao_crunch_example/models/random_forest/submissions/main.py
crunchdao_crunch_example/models/random_forest/submissions/requirements.txt
crunchdao_crunch_example/models/svm/resources/scaler.pkl
crunchdao_crunch_example/models/svm/resources/svm_model.pkl
crunchdao_crunch_example/models/svm/submissions/main.py
crunchdao_crunch_example/models/svm/submissions/requirements.txt
crunchdao_crunch_example/scripts/cleanup_docker.py
crunchdao_crunch_example/scripts/pretrain_models.py
crunchdao_crunch_example/scripts/pretrain_neural_network.py
crunchdao_crunch_example/scripts/sync_models.py
crunchdao_crunch_example/scripts/sync_models_quick.py
crunchdao/__init__.py
crunchdao/crunch_example/__init__.py
crunchdao/crunch_example/iris/__init__.py
crunchdao/crunch_example/iris/model_base.py
crunchdao_crunch_example-0.3.2.dist-info/METADATA
crunchdao_crunch_example-0.3.2.dist-info/WHEEL
crunchdao_crunch_example-0.3.2.dist-info/licenses/LICENSE
crunchdao_crunch_example-0.3.2.dist-info/RECORD
