Metadata-Version: 2.4
Name: crunchdao-crunch-example
Version: 0.3.2
Summary: CrunchDAO example packages for machine learning competitions
Project-URL: Homepage, https://github.com/crunchdao/coordinator-setup
Project-URL: Documentation, https://docs.crunchdao.com
Project-URL: Repository, https://github.com/crunchdao/coordinator-setup
Project-URL: Issues, https://github.com/crunchdao/coordinator-setup/issues
Author-email: CrunchDAO <boris.nieuwenhuis@crunchdao.com>
License: MIT License
License-File: LICENSE
Keywords: classification,competition,crunchdao,iris,machine learning
Classifier: Development Status :: 3 - Alpha
Classifier: Intended Audience :: Developers
Classifier: Intended Audience :: Science/Research
Classifier: License :: OSI Approved :: MIT License
Classifier: Operating System :: OS Independent
Classifier: Programming Language :: Python :: 3
Classifier: Programming Language :: Python :: 3.11
Classifier: Programming Language :: Python :: 3.12
Classifier: Topic :: Scientific/Engineering :: Artificial Intelligence
Classifier: Topic :: Software Development :: Libraries :: Python Modules
Requires-Python: >=3.11
Requires-Dist: numpy>=1.21.0
Requires-Dist: pandas>=2.0.0
Requires-Dist: scikit-learn>=1.0.0
Provides-Extra: dev
Requires-Dist: black>=23.0; extra == 'dev'
Requires-Dist: isort>=5.0; extra == 'dev'
Requires-Dist: mypy>=1.0; extra == 'dev'
Requires-Dist: pytest-cov>=4.0; extra == 'dev'
Requires-Dist: pytest>=7.0; extra == 'dev'
